pytorch_eff_vis_pretraining/__init__.py
pytorch_eff_vis_pretraining/download.py
pytorch_eff_vis_pretraining/layers.py
pytorch_eff_vis_pretraining/resnet.py
pytorch_eff_vis_pretraining-1.0.1.dist-info/LICENSE
pytorch_eff_vis_pretraining-1.0.1.dist-info/METADATA
pytorch_eff_vis_pretraining-1.0.1.dist-info/WHEEL
pytorch_eff_vis_pretraining-1.0.1.dist-info/top_level.txt
pytorch_eff_vis_pretraining-1.0.1.dist-info/RECORD
